{
  "run_id": "2026-07-17_09-12-25",
  "started_at": "2026-07-17T09:12:25.234787",
  "status": "complete",
  "steps_completed": [
    "analysis",
    "titles",
    "description",
    "thumbnail",
    "evaluation"
  ],
  "data": {
    "analysis": {
      "topic": "ارتفاع مفاجئ في أسعار المحروقات بسوريا بعد أسبوعين من خفضها وتخوف من موجة غلاء جديدة",
      "category": "اقتصادي",
      "tone": "تحذيري",
      "summary": "أعلنت وزارة الطاقة السورية عن رفع سعر لتر البنزين إلى 140 ليرة والمازوت إلى 120 ليرة، بعد أسبوعين فقط من قرار خفض الأسعار. المواطنون عبروا عن قلقهم من تداعيات هذا الارتفاع على تكاليف المعيشة، في ظل صعود أسعار النفط العالمية وتراجع القدرة الشرائية للسوريين.",
      "people": [
        "محمد البشير"
      ],
      "organizations": [
        "وزارة الطاقة",
        "تلفزيون سوريا",
        "اللجنة الدائمة لتحديد أسعار المواد البترولية والثروات المعدنية"
      ],
      "countries": [
        "سوريا"
      ],
      "locations": [],
      "keywords": [
        "ارتفاع اسعار المحروقات في سوريا",
        "سعر البنزين اليوم في سوريا",
        "سعر المازوت الجديد",
        "وزارة الطاقة السورية",
        "محمد البشير وزير الطاقة",
        "ازمة المحروقات في سوريا",
        "غلاء الاسعار في سوريا",
        "اسعار النفط العالمية",
        "اخبار سوريا اليوم",
        "القدرة الشرائية للسوريين",
        "محطات الوقود سوريا",
        "اللجنة الدائمة لتسعير المحروقات",
        "تكاليف المعيشة في سوريا"
      ],
      "important_quotes": [
        "والله بالنسبة لسعر البنزين ارتفع امبارح كان 12 و500 اليوم 14000",
        "المهم يتوفر يعني الاهم من كل هذا انه ما نضل واقفين اربع خمس ساعات على الدور"
      ],
      "youtube_angle": "لماذا ارتفعت أسعار المحروقات في سوريا بعد أسبوعين فقط من خفضها؟ وهل يواجه السوريون موجة غلاء جديدة؟",
      "title_focus": "ارتفاع مفاجئ في أسعار البنزين والمازوت بسوريا وتخوف من غلاء شامل",
      "thumbnail_focus": "طابور سيارات أمام محطة وقود مع صورة لأرقام أسعار البنزين الجديدة",
      "search_intent": "informational",
      "emotion": "قلق",
      "urgency_level": "مهم",
      "target_audience": "سوريون"
    },
    "titles": {
      "titles": [
        {
          "text": "بعد أسبوعين فقط من خفضها.. ارتفاع مفاجئ بأسعار المحروقات في سوريا",
          "style": "خبر مباشر",
          "length": 67,
          "rationale": "يبرز المفارقة الزمنية التي تشكل صلب المفاجأة الإخبارية"
        },
        {
          "text": "وزارة الطاقة ترفع سعر البنزين والمازوت.. وتخوف من موجة غلاء جديدة",
          "style": "خبر مباشر",
          "length": 67,
          "rationale": "يذكر الجهة الرسمية والفعل مباشرة مع النتيجة المتوقعة"
        },
        {
          "text": "لماذا ارتفعت أسعار المحروقات في سوريا بعد خفضها بأسبوعين؟",
          "style": "سؤال تحليلي",
          "length": 58,
          "rationale": "يطرح التساؤل الذي يشغل الجمهور حول أسباب التذبذب المفاجئ"
        },
        {
          "text": "خفض ثم ارتفاع.. مسار متقلب لأسعار المحروقات يربك السوريين",
          "style": "مقارنة",
          "length": 58,
          "rationale": "يبرز التناقض بين القرارين المتتاليين خلال أسبوعين فقط"
        },
        {
          "text": "بين الأمل والقلق.. كيف يواجه السوريون غلاء المحروقات الجديد؟",
          "style": "تشويق",
          "length": 61,
          "rationale": "يعكس حالة الانقسام العاطفي لدى المواطنين تجاه القرار"
        },
        {
          "text": "مواطنون يعبرون عن غضبهم من ارتفاع مفاجئ في أسعار البنزين والمازوت",
          "style": "رأي شعبي",
          "length": 66,
          "rationale": "يستند إلى اقتباسات المواطنين ويعطي بعداً إنسانياً للخبر"
        },
        {
          "text": "أسعار النفط العالمية تدفع سوريا نحو موجة غلاء جديدة",
          "style": "خبر مباشر",
          "length": 53,
          "rationale": "يربط السبب الخارجي بالتأثير المحلي المباشر على المواطن"
        },
        {
          "text": "هل تتحمل القدرة الشرائية للسوريين ارتفاعا جديدا في المحروقات؟",
          "style": "سؤال تحليلي",
          "length": 61,
          "rationale": "يوجه التركيز نحو البعد الاقتصادي الأخطر وهو القدرة الشرائية"
        },
        {
          "text": "140 ليرة للبنزين و120 للمازوت.. تفاصيل التسعيرة الجديدة في سوريا",
          "style": "خبر مباشر",
          "length": 65,
          "rationale": "يقدم الأرقام الدقيقة التي يبحث عنها الجمهور مباشرة"
        },
        {
          "text": "بعد أسبوعين من الفرح بانخفاضها.. المحروقات ترتفع مجدداً في سوريا",
          "style": "تشويق",
          "length": 65,
          "rationale": "يبني تشويقاً درامياً حول انعكاس القرار خلال وقت قصير"
        }
      ],
      "recommended": {
        "index": 0,
        "reason": "هذا العنوان يجمع بين الإيجاز والوضوح، ويبرز أقوى عنصر مفاجئ في القصة وهو التناقض الزمني السريع بين الخفض والارتفاع، وهو ما يثير فضول المشاهد فوراً، كما يتماشى مع أسلوب تلفزيون سوريا في العناوين المباشرة المدعومة بسياق زمني."
      },
      "notes": "تم التركيز على الزاوية الزمنية (أسبوعين) لأنها العنصر الأكثر إثارة للدهشة، مع تنويع بين العناوين الرقمية والتحليلية والشعبية لتغطية جمهور واسع."
    },
    "description": {
      "description": "تشهد الأسواق السورية حالة من التخبط عقب قرار وزارة الطاقة برفع أسعار المحروقات بشكل مفاجئ، وذلك بعد أقل من أسبوعين على خفضها. يأتي هذا الإجراء وسط مخاوف شعبية واسعة من انعكاسات القرار على تكاليف المعيشة المتفاقمة أصلاً.\n\nتأتي هذه الخطوة في ظل تقلبات أسعار النفط العالمية وتراجع القدرة الشرائية للمواطنين، حيث أثار التعديل السعري الجديد استياءً في الشارع السوري، خاصة مع استمرار أزمات التوفر والانتظار الطويل أمام محطات الوقود. وتتجه الأنظار نحو تأثير هذه القرارات على أسعار السلع الأساسية وقطاع النقل في المرحلة المقبلة.\n\nلمتابعة آخر الأخبار الاقتصادية والسياسية في سوريا، اشتركوا في قناة تلفزيون سوريا على يوتيوب وفعلوا جرس التنبيهات ليصلكم كل جديد.",
      "keywords": [
        "ارتفاع اسعار المحروقات في سوريا",
        "سعر البنزين اليوم في سوريا",
        "سعر المازوت الجديد",
        "وزارة الطاقة السورية",
        "ازمة المحروقات في سوريا",
        "غلاء الاسعار في سوريا",
        "القدرة الشرائية للسوريين",
        "اخبار سوريا اليوم",
        "اقتصاد سوريا",
        "تلفزيون سوريا",
        "اسعار النفط العالمية",
        "محمد البشير"
      ],
      "hashtags": [
        "#سوريا",
        "#أخبار_سوريا",
        "#تلفزيون_سوريا",
        "#المحروقات",
        "#اقتصاد_سوريا",
        "#غلاء_الأسعار",
        "#أزمة_الوقود"
      ],
      "notes": "تم الالتزام بقواعد الاصطلاحات الإملائية وعدم إدراج هاشتاغات داخل نص الوصف."
    },
    "thumbnail": {
      "options": [
        {
          "text": "صدمة عند المضخة",
          "word_count": 3,
          "visual_note": "لقطة قريبة (close-up) لوجه سائق داخل سيارته وهو ينظر بذهول نحو شاشة المضخة الرقمية، مع تعبير صدمة حقيقي (حواجب مرتفعة، فم نصف مفتوح). الإضاءة سينمائية باردة من أضواء المحطة ليلاً، مع خلفية مطموسة (depth of field) لطابور السيارات خلف الزجاج. الألوان: أصفر/برتقالي أضواء المحطة مقابل أزرق داكن للخلفية لخلق تباين قوي. فجوة الفضول: الشاشة تظهر جزئياً فقط، فيتساءل المشاهد كم أصبح السعر فعلاً."
        },
        {
          "text": "غلاء يطرق الأبواب",
          "word_count": 3,
          "visual_note": "تكوين يجمع بين طابور طويل من السيارات في المقدمة (ضبابي قليلاً) ووجه سائق واحد حاد التركيز في المنتصف يظهر قلقاً وتوتراً. إضاءة الغروب الحمراء/البرتقالية تُستخدم كإنذار بصري، مع سماء داكنة تدريجياً نحو الأسود في الأعلى لترك مساحة للنص. الفضول: لا تظهر الأرقام كاملة، فقط طرف لوحة الأسعار الجديدة، ما يدفع المشاهد للنقر لمعرفة الرقم الكامل."
        },
        {
          "text": "وقود بلا رحمة",
          "word_count": 3,
          "visual_note": "الذات المحورية: يد سائق تمسك بمسدس الوقود بقوة وتوتر واضح على العضلات، مع خلفية طابور سيارات ممتد حتى نقطة تلاشي الأفق. إضاءة درامية جانبية (rim light) تبرز اليد والمسدس كبطل بصري وحيد بمعدل 40% من الكادر. لوحة الألوان: أسود/رمادي معدني للمحطة مقابل بقعة حمراء تحذيرية على شاشة السعر. الفضول يكمن في عدم إظهار الرقم كاملاً، فقط وميض أحمر يوحي بالخطر."
        },
        {
          "text": "أرقام تؤلم الجيب",
          "word_count": 3,
          "visual_note": "الصورة تعتمد على تباين حجمي: شاشة مضخة الوقود بأرقام كبيرة صفراء مضيئة تحتل الثلث العلوي، وتحتها يد تُخرج محفظة فارغة أو نقوداً قليلة، في إضاءة قاسية تُبرز التفاصيل. الخلفية سوداء تماماً لعزل العنصرين وخلق تركيز بصري واحد لا يتشتت. الفضول: الرقم الفعلي على الشاشة مموه جزئياً بضبابية خفيفة، يدفع المشاهد للضغط لمعرفة الرقم كاملاً."
        },
        {
          "text": "طوابير وغضب متصاعد",
          "word_count": 3,
          "visual_note": "لقطة واسعة (wide shot) لطابور سيارات طويل تحت سماء غائمة داكنة، مع سائق في المقدمة يخرج رأسه من نافذته بتعبير غضب واضح (حاجبان معقودان، فم مفتوح كأنه يصرخ). تدرج إضاءة من الأبيض الساطع عند المحطة إلى الرمادي الداكن في الخلفية لخلق عمق سينمائي. الألوان محدودة بين الأصفر التحذيري وأزرق باهت. الفضول: لا يظهر سبب الغضب مباشرة، بل تعبير الوجه فقط يستدعي السؤال 'ماذا حدث بالضبط؟'"
        },
        {
          "text": "الفاتورة الحقيقية تقع على المواطن",
          "word_count": 5,
          "visual_note": "تكوين ثنائي: في المقدمة رجل من الطبقة المتوسطة (ملابس عادية) يحمل ورقة فاتورة ويحدق فيها بصدمة صامتة، وخلفه بعيداً وخارج التركيز طابور سيارات ينتظر عند المحطة. إضاءة طبيعية نهارية قاسية تُبرز تجاعيد القلق على الوجه. الألوان: أبيض/رمادي محايد للملابس مقابل تفاصيل حمراء صغيرة على الورقة تشير لزيادة السعر. الفضول: الرقم على الورقة غير واضح تماماً، يثير تساؤل 'كم دفع فعلاً؟'"
        },
        {
          "text": "طابور طويل يخفي سؤالاً كبيراً",
          "word_count": 5,
          "visual_note": "لقطة من الأعلى (top-down/drone-like) لطابور سيارات ممتد بشكل هندسي منظم يوحي بالانتظار الطويل، مع نقطة إضاءة واحدة ساطعة عند بداية الطابور (المحطة) وظلام تدريجي كلما ابتعدنا. لا وجود لوجه بشري في هذه النسخة، بل الطابور نفسه هو البطل البصري، ما يخلق غموضاً وفضولاً حول 'لماذا هذا الازدحام المفاجئ؟'. الألوان: أصفر إضاءة المحطة وسط محيط رمادي/أسود لتوجيه العين مباشرة لنقطة الاهتمام."
        },
        {
          "text": "المواطن يدفع الثمن مرة أخرى",
          "word_count": 5,
          "visual_note": "لقطة نصفية لرجل متوسط العمر يجلس خلف مقود سيارته، يداه على عجلة القيادة بقبضة متوترة، ونظراته شاردة نحو الأمام بتعبير إرهاق واستسلام ممزوج بغضب مكتوم. الإضاءة جانبية دافئة (تُذكّر بغروب الشمس) تبرز نصف الوجه وتترك النصف الآخر في ظل خفيف لإضفاء دراما نفسية. خلفية مموهة تماماً تُظهر فقط ألوان محطة الوقود. الفضول: لا نرى المحطة بوضوح، فقط انعكاسها الخافت في عينيه."
        },
        {
          "text": "قرار اقتصادي غامض يشعل الغضب",
          "word_count": 5,
          "visual_note": "تصميم رمزي: يد تشير أو تضغط على زر أحمر وهمي (تمثيل تصويري للقرار) في المقدمة، وخلفها في العمق طابور سيارات ووجوه غاضبة غير واضحة المعالم. إضاءة حمراء تحذيرية قوية تغمر العنصر الأمامي بينما تبقى الخلفية باردة ومظلمة، لخلق تباين حاد بين 'القرار' و'الأثر البشري'. الفضول: لا تُعرف هوية متخذ القرار، فقط رمز اليد، ما يدفع المشاهد لمعرفة من المسؤول."
        },
        {
          "text": "وزارة الطاقة السورية تحت المجهر",
          "word_count": 5,
          "visual_note": "تكوين يجمع بين لافتة أو شعار وزارة الطاقة (بشكل مموه أو من زاوية جانبية) في المقدمة العليا، وتحته مباشرة طابور سيارات حقيقي يمتد للخلف. إضاءة قاسية علوية تشبه إضاءة قاعة تحقيق، مع ظلال حادة تعطي إحساساً بالمساءلة والرقابة. الألوان: رمادي فولاذي بارد مع لمسة صفراء تحذيرية على شعار الوزارة. الفضول: لا يظهر أي مسؤول أو تصريح، فقط الرمز والنتيجة البصرية (الطابور)، ما يثير تساؤل 'من المسؤول عن هذا القرار؟'"
        }
      ],
      "recommended_index": 0
    },
    "evaluation": {
      "overall_score": 85,
      "criteria": [
        {
          "name": "الدقة الصحفية",
          "score": 78,
          "comment": "العنوان أمين للفكرة الأساسية الواردة في التقرير، وهي ارتفاع الأسعار بعد نحو أسبوعين من خفضها. لكن الوصف ينسب الرفع مباشرة إلى «قرار وزارة الطاقة» رغم أن النص يتحدث عن مصدر في الوزارة وبدء التطبيق قبل إعلان رسمي، كما أن عبارة «أقل من أسبوعين» أدقّتها أقل من صياغة النص الأصلي."
        },
        {
          "name": "الالتزام بالاصطلاحات",
          "score": 100,
          "comment": "يستخدم المحتوى مصطلح «سوريا» وفق الدليل المعتمد، ولا يتضمن أي مخالفة اصطلاحية رسمية ظاهرة."
        },
        {
          "name": "جودة الصياغة اللغوية",
          "score": 92,
          "comment": "الصياغة سليمة وواضحة ومناسبة للنشر، مع تسلسل منطقي بين القرار المحتمل وتداعياته. إلا أن تعبير «حالة من التخبط» يحمل حكماً عاماً غير مسند بوضوح في النص الأصلي، والأفضل استبداله بصياغة أكثر تحديداً."
        },
        {
          "name": "قوة الجذب (Hook)",
          "score": 87,
          "comment": "العنوان يقدّم مفارقة زمنية جاذبة بين الخفض والرفع السريع، ونص الثمبنيل قصير وواضح. غير أن «صدمة عند المضخة» صياغة مألوفة وعامة، ويمكن تقويتها بإبراز الارتفاع السعري أو أثره المباشر."
        },
        {
          "name": "التوافق بين العنوان والوصف والثمبنيل",
          "score": 83,
          "comment": "العناصر الثلاثة تتمحور حول ارتفاع أسعار المحروقات وانعكاسه على المواطنين. لكن الثمبنيل يركّز على رد فعل فردي عام، بينما الوصف يوسّع القصة إلى أثر اقتصادي وأزمات التوفر، من دون أن يوضح البريف السعر الجديد أو دلالة الزيادة."
        },
        {
          "name": "الطول والصيغة الفنية",
          "score": 93,
          "comment": "العنوان يقع ضمن المدى المناسب تقريباً ويحافظ على وضوحه، والوصف مكوّن من ثلاث فقرات فعلاً. الفقرة الأخيرة دعائية للقناة أكثر من كونها جزءاً تحريرياً من الوصف، لكنها لا تخل بالصيغة الفنية المطلوبة."
        }
      ],
      "strengths": [
        "العنوان ينقل الحدث الرئيسي بوضوح ويبرز سرعة التحول من خفض الأسعار إلى رفعها.",
        "المحتوى ملتزم بالاصطلاح الرسمي «سوريا».",
        "الوصف يربط الارتفاع بتكاليف المعيشة والنقل والسلع، وهي زاوية متسقة مع التقرير.",
        "فكرة الثمبنيل قابلة للتنفيذ بصرياً وتحتوي تبايناً لونياً مناسباً للفت الانتباه.",
        "التقسيم إلى ثلاث فقرات يجعل الوصف سهل القراءة على يوتيوب."
      ],
      "weaknesses": [
        "نسبة رفع الأسعار إلى «قرار وزارة الطاقة» تتجاوز ما يؤكده النص، الذي يتحدث عن مصدر وزاري وتطبيق قبل إعلان رسمي.",
        "عبارة «بعد أقل من أسبوعين» أقل دقة من الأصل الذي يقول «بعد نحو أسبوعين».",
        "وصف الأسواق بأنها في «حالة من التخبط» حكم تفسيري غير موثق بشكل مباشر في التقرير.",
        "الثمبنيل لا يستثمر المعلومة الأكثر ملموسية، وهي السعر الجديد للبنزين والمازوت أو الزيادة المفاجئة.",
        "التركيز على «استمرار أزمات التوفر» يحتاج تحفّظاً، لأن التقرير يشير إلى الاقتراب من نهاية الأزمة مع بقاء مخاوف من الطوابير."
      ],
      "verdict": "جاهز للنشر مع تعديل طفيف في الدقة التحريرية.",
      "ready_to_publish": true
    }
  },
  "cost_so_far_usd": 0.128739,
  "last_updated": "2026-07-17T09:14:30.961699",
  "completed_at": "2026-07-17T09:14:30.963180"
}